md2all/__init__.py
md2all/cli.py
md2all/md_to_html.py
md2all/utils.py
md2all/libs/custom_css.css
md2all/libs/tailwind.min.css
md2all/libs/tex-mml-chtml.js
md2all-0.0.10.data/data/assets/custom_css.css
md2all-0.0.10.data/data/assets/tailwind.min.css
md2all-0.0.10.data/data/assets/tex-mml-chtml.js
md2all-0.0.10.dist-info/LICENSE
md2all-0.0.10.dist-info/METADATA
md2all-0.0.10.dist-info/WHEEL
md2all-0.0.10.dist-info/entry_points.txt
md2all-0.0.10.dist-info/top_level.txt
md2all-0.0.10.dist-info/RECORD
