Metadata-Version: 2.1
Name: md2all
Version: 0.0.10
Summary: convertor is a simple and easy to use library for converting markdown files to various formats.
Home-page: https://github.com/codeperfectplus/md2all
Author: Deepak Raj
Author-email: deepak008@live.com
Project-URL: Documentation, https://md2all.readthedocs.io/en/latest/
Project-URL: Source, https://github.com/codeperfectplus/md2all
Project-URL: Tracker, https://github.com/codeperfectplus/md2all/issues
Classifier: Development Status :: 5 - Production/Stable
Classifier: Programming Language :: Python :: 3
Classifier: License :: OSI Approved :: Apache Software License
Classifier: Operating System :: OS Independent
Classifier: Intended Audience :: Developers
Requires-Python: >=3.6
License-File: LICENSE
Requires-Dist: beautifulsoup4==4.13.4
Requires-Dist: markdown==3.8
Requires-Dist: playwright==1.51.0
Requires-Dist: asyncio==3.4.3
Requires-Dist: aiofiles==24.1.0
